LICENSE.txt
MANIFEST.in
README.md
mkdocs.yml
requirements.txt
setup.cfg
setup.py
tox.ini
docs/CloudManager.md
docs/Firewall.md
docs/IP-address-mixin.md
docs/IP-address.md
docs/Server.md
docs/Storage.md
docs/index.md
docs/server-mixin.md
docs/storage-mixin.md
test/conftest.py
test/test_cloud_manager.py
test/test_firewall.py
test/test_ip_manager.py
test/test_server.py
test/test_server_creation.py
test/test_storage.py
test/json_data/account.json
test/json_data/firewall_rule.json
test/json_data/firewall_rules.json
test/json_data/ip_address.json
test/json_data/ip_address_10.1.0.101.json
test/json_data/ip_address_post.json
test/json_data/price.json
test/json_data/server.json
test/json_data/server_00798b85-efdc-41ca-8021-f6ef457b8531.json
test/json_data/server_009d64ef-31d1-4684-a26b-c86c955cbf46.json
test/json_data/server_create.json
test/json_data/storage_01d4fcd4-e446-433b-8a9c-551a1284952e.json
test/json_data/storage_attach.json
test/json_data/storage_detach.json
test/json_data/storage_post.json
test/json_data/storage_public.json
test/json_data/timezone.json
test/json_data/zone.json
upcloud/__init__.py
upcloud/base.py
upcloud/firewall.py
upcloud/ip_address.py
upcloud/server.py
upcloud/storage.py
upcloud/tools.py
upcloud/cloud_manager/__init__.py
upcloud/cloud_manager/cloud_manager.py
upcloud/cloud_manager/firewall_mixin.py
upcloud/cloud_manager/ip_address_mixin.py
upcloud/cloud_manager/server_mixin.py
upcloud/cloud_manager/storage_mixin.py
upcloud_api_python.egg-info/PKG-INFO
upcloud_api_python.egg-info/SOURCES.txt
upcloud_api_python.egg-info/dependency_links.txt
upcloud_api_python.egg-info/requires.txt
upcloud_api_python.egg-info/top_level.txt