Metadata-Version: 1.0
Name: upcloud-api-python
Version: 0.2.0
Summary: UpCloud API Client
Home-page: https://github.com/UpCloudLtd/upcloud-python-api
Author: Elias Nygren
Author-email: elias.nygren@upcloud.com
License: MIT
Platform: UNKNOWN
